core/__init__.py
core/main.py
core/runner.py
http_scanner-0.1.12.dist-info/licenses/LICENSE
plugins/inputs/__init__.py
plugins/inputs/http_input.py
plugins/outputs/__init__.py
plugins/outputs/console_output.py
plugins/outputs/json_output.py
plugins/processors/__init__.py
plugins/processors/idea_extractor.py
http_scanner-0.1.12.dist-info/METADATA
http_scanner-0.1.12.dist-info/WHEEL
http_scanner-0.1.12.dist-info/top_level.txt
http_scanner-0.1.12.dist-info/RECORD
