Metadata-Version: 2.4
Name: http-scanner
Version: 0.1.12
Summary: A modular, plugin-based HTTP scanning framework.
Author-email: dotcomrow <administrator@suncoast.systems>
License-Expression: MIT
Project-URL: Homepage, https://github.com/dotcomrow/http-scanner
Project-URL: Source, https://github.com/dotcomrow/http-scanner
Project-URL: Tracker, https://github.com/dotcomrow/http-scanner/issues
Keywords: scanner,http,plugins,ai,automation
Requires-Python: >=3.8
License-File: LICENSE
Requires-Dist: requests
Requires-Dist: beautifulsoup4
Requires-Dist: PyYAML
Requires-Dist: httpx
Dynamic: license-file
